richprompt/__init__.py
richprompt/magic.py
richprompt/prompts.py
richprompt/startup.py
richprompt/timer.py
richprompt-0.2.0.dist-info/LICENSE
richprompt-0.2.0.dist-info/METADATA
richprompt-0.2.0.dist-info/WHEEL
richprompt-0.2.0.dist-info/entry_points.txt
richprompt-0.2.0.dist-info/top_level.txt
richprompt-0.2.0.dist-info/RECORD
