Metadata-Version: 2.1
Name: richprompt
Version: 0.2.0
Summary: A better IPython prompt
Home-page: https://github.com/lewisacidic/richprompt
Author: Rich Lewis
Author-email: opensource@richlew.is
License: MIT
Keywords: ipython,prompt
Platform: UNKNOWN
Requires-Dist: ipython
Provides-Extra: hook
Requires-Dist: ipython-startup-hook ; extra == 'hook'
